babyrl/__about__.py
babyrl/__init__.py
babyrl/core.py
babyrl/ddpg.py
babyrl/ppo.py
babyrl/simplest_pg.py
babyrl/td3.py
babyrl/trpo.py
babyrl/vpg.py
babyrl-0.0.1.dist-info/METADATA
babyrl-0.0.1.dist-info/WHEEL
babyrl-0.0.1.dist-info/licenses/LICENSE.txt
babyrl-0.0.1.dist-info/RECORD
